k9/__init__.py
k9/client/__init__.py
k9/middleware/__init__.py
k9/middleware/fastapi/__init__.py
k9/models/__init__.py
k9_python_logger-0.0.19.dist-info/METADATA
k9_python_logger-0.0.19.dist-info/WHEEL
k9_python_logger-0.0.19.dist-info/top_level.txt
k9_python_logger-0.0.19.dist-info/RECORD
