Metadata-Version: 2.1
Name: k9-python-logger
Version: 0.0.19
Summary: official python logger library for k9
Requires-Python: >=3.7
Requires-Dist: jsonschema (==4.16.0)
Requires-Dist: jsonpatch (==1.32)
